flame_core/__init__.py
flame_core/emperor/__init__.py
flame_core/emperor/_emperor.py
flame_core/emperor/_exception.py
flame_core/emperor/workflow.py
flame_core/nomadic/__init__.py
flame_core/nomadic/async_qdrant_vector.py
flame_core/nomadic/basic_splitter_text.py
flame_core/nomadic/text_splitter.py
flame_core/weapons/__init__.py
flame_core/weapons/context.py
flame_core/weapons/context_model.py
flame_core-0.1.2.dist-info/LICENSE
flame_core-0.1.2.dist-info/METADATA
flame_core-0.1.2.dist-info/WHEEL
flame_core-0.1.2.dist-info/top_level.txt
flame_core-0.1.2.dist-info/RECORD
