Metadata-Version: 2.2
Name: flame-core
Version: 0.1.2
Summary: A lightweight asynchronous task flow framework
Author-email: lingdubing <3189377462@qq.com>
License: # flame/LICENSE
Project-URL: Homepage, https://github.com/lingdubing-xo/flame
Project-URL: Repository, https://github.com/lingdubing-xo/flame.git
Requires-Python: >=3.8
License-File: LICENSE
Requires-Dist: sentence-transformers>=3.4.1
Requires-Dist: tiktoken>=0.9.0
Requires-Dist: numpy>=2.2.3
Requires-Dist: scikit-learn>=1.6.1
Requires-Dist: qdrant-client>=1.13.3
Provides-Extra: dev
Requires-Dist: pytest>=8.3.5; extra == "dev"
Requires-Dist: pytest-asyncio>=0.25.3; extra == "dev"
Requires-Dist: loguru>=0.7.3; extra == "dev"
